bannedfuncdetector/__init__.py
bannedfuncdetector/__main__.py
bannedfuncdetector/analyzer_exceptions.py
bannedfuncdetector/bannedfunc.py
bannedfuncdetector/cli.py
bannedfuncdetector/constants.py
bannedfuncdetector/factories.py
bannedfuncdetector/file_detection.py
bannedfuncdetector/application/__init__.py
bannedfuncdetector/application/directory_scanner.py
bannedfuncdetector/application/parallel_analyzer.py
bannedfuncdetector/application/binary_analyzer/__init__.py
bannedfuncdetector/application/binary_analyzer/core.py
bannedfuncdetector/application/binary_analyzer/detection.py
bannedfuncdetector/application/binary_analyzer/operations.py
bannedfuncdetector/application/binary_analyzer/reporting.py
bannedfuncdetector/domain/__init__.py
bannedfuncdetector/domain/banned_functions.py
bannedfuncdetector/domain/config_types.py
bannedfuncdetector/domain/entities.py
bannedfuncdetector/domain/protocols.py
bannedfuncdetector/domain/result.py
bannedfuncdetector/domain/types.py
bannedfuncdetector/infrastructure/__init__.py
bannedfuncdetector/infrastructure/config_repository.py
bannedfuncdetector/infrastructure/error_handling.py
bannedfuncdetector/infrastructure/validators.py
bannedfuncdetector/infrastructure/adapters/__init__.py
bannedfuncdetector/infrastructure/adapters/r2_client.py
bannedfuncdetector/infrastructure/adapters/r2ai_server.py
bannedfuncdetector/infrastructure/decompilers/__init__.py
bannedfuncdetector/infrastructure/decompilers/availability.py
bannedfuncdetector/infrastructure/decompilers/base_decompiler.py
bannedfuncdetector/infrastructure/decompilers/cascade.py
bannedfuncdetector/infrastructure/decompilers/decai_decompiler.py
bannedfuncdetector/infrastructure/decompilers/default_decompiler.py
bannedfuncdetector/infrastructure/decompilers/orchestrator.py
bannedfuncdetector/infrastructure/decompilers/r2dec_decompiler.py
bannedfuncdetector/infrastructure/decompilers/r2ghidra_decompiler.py
bannedfuncdetector/infrastructure/decompilers/registry.py
bannedfuncdetector-2.0.0.dist-info/METADATA
bannedfuncdetector-2.0.0.dist-info/WHEEL
bannedfuncdetector-2.0.0.dist-info/entry_points.txt
bannedfuncdetector-2.0.0.dist-info/top_level.txt
bannedfuncdetector-2.0.0.dist-info/RECORD
