Metadata-Version: 2.4
Name: bannedfuncdetector
Version: 2.0.0
Summary: Detects banned/insecure functions in binary files using radare2 decompilers.
Author-email: Marc Rivero López <mriverolopez@gmail.com>
Maintainer-email: Marc Rivero López <mriverolopez@gmail.com>
License: GPL-3.0-or-later
Project-URL: Homepage, https://github.com/seifreed/BannedFuncDetector
Project-URL: Repository, https://github.com/seifreed/BannedFuncDetector
Project-URL: Issues, https://github.com/seifreed/BannedFuncDetector/issues
Project-URL: Documentation, https://github.com/seifreed/BannedFuncDetector#readme
Keywords: security,binary-analysis,radare2,decompiler,banned-functions,vulnerability-detection,malware-analysis,reverse-engineering
Classifier: Development Status :: 4 - Beta
Classifier: Environment :: Console
Classifier: Intended Audience :: Developers
Classifier: Intended Audience :: Information Technology
Classifier: Intended Audience :: Science/Research
Classifier: License :: OSI Approved :: GNU General Public License v3 or later (GPLv3+)
Classifier: Operating System :: OS Independent
Classifier: Programming Language :: Python :: 3
Classifier: Programming Language :: Python :: 3.12
Classifier: Programming Language :: Python :: 3.13
Classifier: Topic :: Security
Classifier: Topic :: Software Development :: Disassemblers
Classifier: Typing :: Typed
Requires-Python: >=3.12
Requires-Dist: r2pipe>=1.9.6
Requires-Dist: python-magic>=0.4.27
Requires-Dist: requests>=2.32.5
